LICENSE
MANIFEST.in
README.md
setup.py
chagallpy/__init__.py
chagallpy/argument_parser.py
chagallpy/exif_data_reader.py
chagallpy/gallery_info.py
chagallpy/gallery_info_reader.py
chagallpy/gallery_page_creator.py
chagallpy/image_collector.py
chagallpy/image_info.py
chagallpy/image_page_creator.py
chagallpy/image_resizer.py
chagallpy/image_sorter.py
chagallpy/meta_data_reader.py
chagallpy/resource_copy.py
chagallpy/thumbnail_creator.py
chagallpy.egg-info/PKG-INFO
chagallpy.egg-info/SOURCES.txt
chagallpy.egg-info/dependency_links.txt
chagallpy.egg-info/entry_points.txt
chagallpy.egg-info/requires.txt
chagallpy.egg-info/top_level.txt
chagallpy/resources/gallery.js
chagallpy/resources/style.css
chagallpy/templates/image_page.html
chagallpy/templates/index.html