Metadata-Version: 2.1
Name: chagallpy
Version: 0.1.5
Summary: CHArming GALLery in PYthon
Home-page: https://github.com/janpipek/chagallpy
Author: Jan Pipek
Author-email: jan.pipek@gmail.com
License: MIT
Platform: UNKNOWN
Requires-Python: ~=3.6
